gmsfile/__init__.py
gmsfile/basis.py
gmsfile/gmsfile.py
gmsfile/irc.py
gmsfile/method.py
gmsfile/runtyp.py
gmsfile/writefile.py
gmsfile-0.1.4.dist-info/LICENSE
gmsfile-0.1.4.dist-info/METADATA
gmsfile-0.1.4.dist-info/WHEEL
gmsfile-0.1.4.dist-info/top_level.txt
gmsfile-0.1.4.dist-info/RECORD
